{
  "frames": {
    "knife0.png": {
      "frame": { "x": 0, "y": 0, "w": 16, "h": 16 },
      "rotated": false,
      "trimmed": false,
      "spriteSourceSize": { "x": 0, "y": 0, "w": 16, "h": 16 },
      "sourceSize": { "w": 16, "h": 16 }
    },
    "knife1.png": {
      "frame": { "x": 0, "y": 16, "w": 16, "h": 16 },
      "rotated": false,
      "trimmed": false,
      "spriteSourceSize": { "x": 0, "y": 0, "w": 16, "h": 16 },
      "sourceSize": { "w": 16, "h": 16 }
    }
  },
  "animations": {
    "knife-glow": ["knife0.png", "knife1.png"]
  },
  "meta": {
    "app": "https://github.com/piskelapp/piskel/",
    "version": "1.0",
    "image": "knife-glow.png",
    "format": "RGBA8888",
    "size": { "w": 16, "h": 32 }
  }
}
